cubicweb_geocoding/__init__.py
cubicweb_geocoding/__pkginfo__.py
cubicweb_geocoding/geocoding.py
cubicweb_geocoding/site_cubicweb.py
cubicweb_geocoding/views.py
cubicweb_geocoding/data/cubicweb.gmap.js
cubicweb_geocoding/data/gmap.utility.labeledmarker.js
cubicweb_geocoding/data/gmap_blue_marker.png
cubicweb_geocoding/i18n/en.po
cubicweb_geocoding/i18n/es.po
cubicweb_geocoding/i18n/fr.po
cubicweb_geocoding-1.1.0.dist-info/METADATA
cubicweb_geocoding-1.1.0.dist-info/WHEEL
cubicweb_geocoding-1.1.0.dist-info/entry_points.txt
cubicweb_geocoding-1.1.0.dist-info/top_level.txt
cubicweb_geocoding-1.1.0.dist-info/RECORD
